demogepsum/__init__.py
demogepsum/demoadd.py
demogepsum-0.1.dist-info/METADATA
demogepsum-0.1.dist-info/WHEEL
demogepsum-0.1.dist-info/top_level.txt
demogepsum-0.1.dist-info/RECORD
