Metadata-Version: 2.1
Name: demogepsum
Version: 0.1
Summary: Testing installation of Package
Home-page: https://github.com/jugal
Author: jugal gohil
Author-email: jugal.gohil@gep.com
License: GEP
Platform: UNKNOWN
